[{"Brand":"","Label":"","Title":"Frozen Turkey Breast","Link":"https://www.myapp.com/product/meatseafood/metur1-frozen-turkey-breast","Sku":"METUR1","Price":"$3.99/LB  | 20 LB AVG","Unit":"LB","Img":"https://cdn-endpoint-website.azureedge.net/uploads/PhotoModel/18177/image/metur1.search.jpg?t=1504645673","ProductKey":"ProductModel_metur1","Category":"meatseafood"},{"Brand":"KOCH'S TURKEY","Label":"local","Title":"Frozen Organic Turkey 20-24 LB 2 Pieces","Link":"https://www.myapp.com/product/meatseafood/metur10ko-frozen-organic-turkey-204524-lb-2-pieces","Sku":"METUR10KO","Price":"$5.99/LB  | 40 LB AVG | 2 PC","Unit":"LB","Img":"https://cdn-endpoint-website.azureedge.net/uploads/PhotoModel/25061/image/metur10moriginal.search.jpg?t=1574348047","ProductKey":"ProductModel_metur10ko","Category":"meatseafood"},{"Brand":"KOCH'S TURKEY","Label":"local","Title":"Frozen Skin On Bone-In Thighs","Link":"https://www.myapp.com/product/meatseafood/metur15-frozen-skin-on-bone45in-thighs","Sku":"METUR15","Price":"$3.49/LB  | 36.16 LB AVG","Unit":"LB","Img":"https://cdn-endpoint-website.azureedge.net/uploads/PhotoModel/18321/image/metur15.search.jpg?t=1505163937","ProductKey":"ProductModel_metur15","Category":"meatseafood"},{"Brand":"KOCH'S TURKEY","Label":"local","Title":"Boneless Skin On Turkey Breasts","Link":"https://www.myapp.com/product/meatseafood/metur16so-boneless-skin-on-turkey-breasts","Sku":"METUR16SO","Price":"$5.99/LB  | 36.16 LB AVG | 8 PC","Unit":"LB","Img":"https://cdn-endpoint-website.azureedge.net/uploads/PhotoModel/11193/image/metur16so.search.jpg?t=1473485794","ProductKey":"ProductModel_metur16so","Category":"meatseafood"},{"Brand":"KOCH'S TURKEY","Label":"local","Title":"ABF Frozen Bone-In Turkey Breasts","Link":"https://www.myapp.com/product/meatseafood/metur17m9-abf-frozen-bone45in-turkey-breasts","Sku":"METUR17M9","Price":"$3.99/LB  | 35 LB AVG | 4 PC","Unit":"LB","Img":"https://cdn-endpoint-website.azureedge.net/uploads/PhotoModel/25010/image/metur17m9.search.jpg?t=1573491561","ProductKey":"ProductModel_metur17m9","Category":"meatseafood"},{"Brand":"","Label":"","Title":"Frozen Packed Ground Turkey","Link":"https://www.myapp.com/product/meatseafood/metur2-frozen-packed-ground-turkey","Sku":"METUR2","Price":"$60.99 / 2 X 10 LB","Unit":"CTN","Img":"https://cdn-endpoint-website.azureedge.net/uploads/PhotoModel/18269/image/image126.search.jpg?t=1504817834","ProductKey":"ProductModel_metur2","Category":"meatseafood"},{"Brand":"KOCH'S TURKEY","Label":"local","Title":"Frozen Turkey Sausage Patties","Link":"https://www.myapp.com/product/meatseafood/metur20a-frozen-turkey-sausage-patties","Sku":"METUR20A","Price":"$5.99/LB  | 10 LB AVG","Unit":"LB","Img":"https://cdn-endpoint-website.azureedge.net/uploads/PhotoModel/11322/image/turk.search.jpg?t=1465827459","ProductKey":"ProductModel_metur20a","Category":"meatseafood"},{"Brand":"KOCH'S TURKEY","Label":"local","Title":"Ground Turkey","Link":"https://www.myapp.com/product/meatseafood/metur2f-ground-turkey","Sku":"METUR2F","Price":"$4.99/LB  | 10 LB AVG","Unit":"LB","Img":"https://cdn-endpoint-website.azureedge.net/uploads/PhotoModel/14800/image/metur2f.search.jpg?t=1492030968","ProductKey":"ProductModel_metur2f","Category":"meatseafood"},{"Brand":"KOCH'S TURKEY","Label":"local","Title":"Frozen Ground Turkey","Link":"https://www.myapp.com/product/meatseafood/metur2retail-frozen-ground-turkey","Sku":"METUR2RETAIL","Price":"$98.99 / 20 X 1 LB","Unit":"CTN","Img":"https://cdn-endpoint-website.azureedge.net/uploads/PhotoModel/11128/image/metur2retail.search.jpg?t=1465832514","ProductKey":"ProductModel_metur2retail","Category":"meatseafood"},{"Brand":"KOCH'S TURKEY","Label":"","Title":"Ground Turkey","Link":"https://www.myapp.com/product/meatseafood/metur2rp-ground-turkey","Sku":"METUR2RP","Price":"$5.99 / 1 LB","Unit":"","Img":"https://cdn-endpoint-website.azureedge.net/uploads/PhotoModel/28650/image/metur2rp1.search.jpg?t=1593562212","ProductKey":"","Category":"meatseafood"},{"Brand":"KOCH'S TURKEY","Label":"local","Title":"Frozen Turkey Burgers","Link":"https://www.myapp.com/product/meatseafood/metur7-frozen-turkey-burgers","Sku":"METUR7","Price":"$67.49 / 40 X 4 OZ","Unit":"CTN","Img":"https://cdn-endpoint-website.azureedge.net/uploads/PhotoModel/20771/image/metur7.search.jpg?t=1527631503","ProductKey":"ProductModel_metur7","Category":"meatseafood"},{"Brand":"NATIONS BEST","Label":"","Title":"Cooked Turkey Breast","Link":"https://www.myapp.com/product/meatseafood/metur8-cooked-turkey-breast","Sku":"METUR8","Price":"$6.99/LB  | 6.6 LB AVG","Unit":"LB","Img":"https://cdn-endpoint-website.azureedge.net/uploads/PhotoModel/18178/image/image-1.search.jpg?t=1504645646","ProductKey":"ProductModel_metur8","Category":"meatseafood"},{"Brand":"NATIONS BEST","Label":"","Title":"Oven Roasted Sliced Golden Legacy Turkey Breast","Link":"https://www.myapp.com/product/meatseafood/metur8sli-oven-roasted-sliced-golden-legacy-turkey-breast","Sku":"METUR8SLI","Price":"$5.99/LB  | 11.5 LB AVG | 6 PC","Unit":"LB","Img":"https://cdn-endpoint-website.azureedge.net/uploads/PhotoModel/23007/image/metur8sli1.search.jpg?t=1552322966","ProductKey":"ProductModel_metur8sli","Category":"meatseafood"}]