[{"Brand":"","Label":"","Title":"Frozen Organic Sliced Bananas","Link":"https://www.myapp.com/product/fruits/ba80c-frozen-organic-sliced-bananas","Sku":"BA80C","Price":"$69.99 / 30 LB","Unit":"CTN","Img":"https://cdn-endpoint-website.azureedge.net/uploads/PhotoModel/17678/image/ba80c.search.jpg?t=1503350143","ProductKey":"ProductModel_ba80c","Category":"fruits"},{"Brand":"","Label":"","Title":"Organic Bananas","Link":"https://www.myapp.com/product/fruits/zba2-organic-bananas","Sku":"ZBA2","Price":"$44.99 / 40 LB","Unit":"CTN","Img":"https://cdn-endpoint-website.azureedge.net/uploads/PhotoModel/12217/image/ba2.search.jpg?t=1470097823","ProductKey":"ProductModel_zba2","Category":"fruits"},{"Brand":"","Label":"","Title":"Organic Banana","Link":"https://www.myapp.com/product/fruits/zba2r-organic-banana","Sku":"ZBA2R","Price":"$2.59 / 1 BUNCH","Unit":"EACH","Img":"https://cdn-endpoint-website.azureedge.net/uploads/PhotoModel/26199/image/zba2r.search.jpg?t=1585839414","ProductKey":"ProductModel_zba2r","Category":"fruits"}]