[{"Brand":"","Label":"","Title":"Baby Candy Cane Beets","Link":"https://www.myapp.com/product/vegetables/bee-baby-candy-cane-beets","Sku":"BEE","Price":"$44.99 / 24 CT","Unit":"CTN","Img":"https://cdn-endpoint-website.azureedge.net/uploads/PhotoModel/10045/image/bee.search.jpg?t=1526652084","ProductKey":"ProductModel_bee","Category":"vegetables"},{"Brand":"","Label":"","Title":"Baby Golden Beets","Link":"https://www.myapp.com/product/vegetables/bee1-baby-golden-beets","Sku":"BEE1","Price":"$49.99 / 24 CT","Unit":"CTN","Img":"https://cdn-endpoint-website.azureedge.net/uploads/PhotoModel/7109/image/bee1.search.jpg?t=1465817082","ProductKey":"ProductModel_bee1","Category":"vegetables"},{"Brand":"","Label":"","Title":"Baby Red Beets","Link":"https://www.myapp.com/product/vegetables/bee2-baby-red-beets","Sku":"BEE2","Price":"$39.99 / 24 CT","Unit":"CTN","Img":"https://cdn-endpoint-website.azureedge.net/uploads/PhotoModel/11100/image/bee2.search.jpg?t=1465820649","ProductKey":"ProductModel_bee2","Category":"vegetables"},{"Brand":"","Label":"","Title":"Mixed Color Baby Beets","Link":"https://www.myapp.com/product/vegetables/bee20-mixed-color-baby-beets","Sku":"BEE20","Price":"$44.99 / 24 CT","Unit":"CTN","Img":"https://cdn-endpoint-website.azureedge.net/uploads/PhotoModel/11725/image/bee20.search.jpg?t=1465929492","ProductKey":"ProductModel_bee20","Category":"vegetables"},{"Brand":"","Label":"","Title":"Beets Cooked Ready to Eat","Link":"https://www.myapp.com/product/vegetables/bee21b-beets-cooked-ready-to-eat","Sku":"BEE21B","Price":"$38.99 / 12 X 500 GR","Unit":"CTN","Img":"https://cdn-endpoint-website.azureedge.net/uploads/PhotoModel/16612/image/bee21b.search.jpg?t=1497648110","ProductKey":"ProductModel_bee21b","Category":"vegetables"},{"Brand":"","Label":"","Title":"Medium-Large Red Beets","Link":"https://www.myapp.com/product/vegetables/bee3-medium45large-red-beets","Sku":"BEE3","Price":"$19.99 / 25 LB","Unit":"CTN","Img":"https://cdn-endpoint-website.azureedge.net/uploads/PhotoModel/16600/image/bee3.search.jpg?t=1497645333","ProductKey":"ProductModel_bee3","Category":"vegetables"},{"Brand":"","Label":"","Title":"Jumbo Red Beets","Link":"https://www.myapp.com/product/vegetables/bee3a-jumbo-red-beets","Sku":"BEE3A","Price":"$20.99 / 25 LB","Unit":"CTN","Img":"https://cdn-endpoint-website.azureedge.net/uploads/PhotoModel/16601/image/bee3a.search.jpg?t=1497645505","ProductKey":"ProductModel_bee3a","Category":"vegetables"},{"Brand":"","Label":"","Title":"Beet Noodles","Link":"https://www.myapp.com/product/vegetables/bee3ab-beet-noodles","Sku":"BEE3AB","Price":"$29.99 / 2 X 5 LB","Unit":"CTN","Img":"https://cdn-endpoint-website.azureedge.net/uploads/PhotoModel/28358/image/bee3ab.search.jpg?t=1591987924","ProductKey":"CutOffPreorderProductModel_bee3ab","Category":"vegetables"},{"Brand":"","Label":"","Title":"Whole Peeled Beets","Link":"https://www.myapp.com/product/vegetables/bee3d-whole-peeled-beets","Sku":"BEE3D","Price":"$49.99 / 4 X 5 LB","Unit":"CTN","Img":"https://cdn-endpoint-website.azureedge.net/uploads/PhotoModel/16603/image/bee3d.search.jpg?t=1501512715","ProductKey":"CutOffPreorderProductModel_bee3d","Category":"vegetables"},{"Brand":"","Label":"","Title":"Whole Peeled Beets","Link":"https://www.myapp.com/product/vegetables/bee3d1-whole-peeled-beets","Sku":"BEE3D1","Price":"$33.99 / 5 LB","Unit":"CTN","Img":"https://cdn-endpoint-website.azureedge.net/uploads/PhotoModel/20287/image/bee3d.search.jpg?t=1524517991","ProductKey":"CutOffPreorderProductModel_bee3d1","Category":"vegetables"},{"Brand":"","Label":"","Title":"Shredded Red Beets","Link":"https://www.myapp.com/product/vegetables/bee3i-shredded-red-beets","Sku":"BEE3I","Price":"$16.99 / 1 X 5 LB","Unit":"CTN","Img":"https://cdn-endpoint-website.azureedge.net/uploads/PhotoModel/17227/image/bee3i.search.jpg?t=1501512715","ProductKey":"CutOffPreorderProductModel_bee3i","Category":"vegetables"},{"Brand":"","Label":"","Title":"Peeled Baby Candy Beets","Link":"https://www.myapp.com/product/vegetables/bee3m-peeled-baby-candy-beets","Sku":"BEE3M","Price":"$149.99 / 1 X 5 LB","Unit":"CTN","Img":"https://cdn-endpoint-website.azureedge.net/uploads/PhotoModel/17914/image/bee3m.search.jpg?t=1504032193","ProductKey":"CutOffPreorderProductModel_bee3m","Category":"vegetables"},{"Brand":"","Label":"","Title":"1/4\" Diced Red Beets","Link":"https://www.myapp.com/product/vegetables/bee3n-147434-diced-red-beets","Sku":"BEE3N","Price":"$16.99 / 1 X 5 LB","Unit":"CTN","Img":"https://cdn-endpoint-website.azureedge.net/uploads/PhotoModel/16609/image/bee3t.search.jpg?t=1497647747","ProductKey":"CutOffPreorderProductModel_bee3n","Category":"vegetables"},{"Brand":"","Label":"","Title":"Peeled Baby Gold Beets","Link":"https://www.myapp.com/product/vegetables/bee3p-peeled-baby-gold-beets","Sku":"BEE3P","Price":"$129.99 / 1 X 5 LB","Unit":"CTN","Img":"https://cdn-endpoint-website.azureedge.net/uploads/PhotoModel/17804/image/bee3p.search.jpg?t=1503956846","ProductKey":"CutOffPreorderProductModel_bee3p","Category":"vegetables"},{"Brand":"","Label":"","Title":"1/2\" Diced Red Beets","Link":"https://www.myapp.com/product/vegetables/bee3r-147234-diced-red-beets","Sku":"BEE3R","Price":"$18.99 / 1 X 5 LB","Unit":"CTN","Img":"https://cdn-endpoint-website.azureedge.net/uploads/PhotoModel/16610/image/bee3t.search.jpg?t=1497647747","ProductKey":"CutOffPreorderProductModel_bee3r","Category":"vegetables"},{"Brand":"","Label":"","Title":"Cubed Red Beets","Link":"https://www.myapp.com/product/vegetables/bee3t-cubed-red-beets","Sku":"BEE3T","Price":"$21.99 / 1 X 5 LB","Unit":"CTN","Img":"https://cdn-endpoint-website.azureedge.net/uploads/PhotoModel/16604/image/bee3t.search.jpg?t=1501613793","ProductKey":"CutOffPreorderProductModel_bee3t","Category":"vegetables"},{"Brand":"","Label":"","Title":"3/4\" Diced Red Beets","Link":"https://www.myapp.com/product/vegetables/bee3y-347434-diced-red-beets","Sku":"BEE3Y","Price":"$54.99 / 4 X 5 LB","Unit":"CTN","Img":"https://cdn-endpoint-website.azureedge.net/uploads/PhotoModel/16611/image/bee3t.search.jpg?t=1497647747","ProductKey":"CutOffPreorderProductModel_bee3y","Category":"vegetables"},{"Brand":"","Label":"","Title":"Large Golden Beets","Link":"https://www.myapp.com/product/vegetables/bee4-large-golden-beets","Sku":"BEE4","Price":"$17.99 / 1/2 BU","Unit":"CTN","Img":"https://cdn-endpoint-website.azureedge.net/uploads/PhotoModel/10312/image/image145.search.jpg?t=1465817082","ProductKey":"ProductModel_bee4","Category":"vegetables"},{"Brand":"","Label":"","Title":"Large Gold Beets","Link":"https://www.myapp.com/product/vegetables/bee4a-large-gold-beets","Sku":"BEE4A","Price":"$27.99 / 22 LB","Unit":"CTN","Img":"https://cdn-endpoint-website.azureedge.net/uploads/PhotoModel/7110/image/image1.search.jpg?t=1465826904","ProductKey":"ProductModel_bee4a","Category":"vegetables"},{"Brand":"","Label":"","Title":"Peeled Gold Beets","Link":"https://www.myapp.com/product/vegetables/bee4b-peeled-gold-beets","Sku":"BEE4B","Price":"$54.99 / 4 X 5 LB","Unit":"CTN","Img":"https://cdn-endpoint-website.azureedge.net/uploads/PhotoModel/17806/image/bee4b.search.jpg?t=1503956845","ProductKey":"CutOffPreorderProductModel_bee4b","Category":"vegetables"},{"Brand":"","Label":"","Title":"Peeled Gold Beets","Link":"https://www.myapp.com/product/vegetables/bee4b1-peeled-gold-beets","Sku":"BEE4B1","Price":"$24.99 / 5 LB","Unit":"CTN","Img":"https://cdn-endpoint-website.azureedge.net/uploads/PhotoModel/19956/image/bee4b.search.jpg?t=1519674073","ProductKey":"CutOffPreorderProductModel_bee4b1","Category":"vegetables"},{"Brand":"","Label":"","Title":"1\" Cubed Golden Beets","Link":"https://www.myapp.com/product/vegetables/bee4d-134-cubed-golden-beets","Sku":"BEE4D","Price":"$129.99 / 4 X 5 LB","Unit":"CTN","Img":"https://cdn-endpoint-website.azureedge.net/uploads/PhotoModel/17915/image/image-1.search.jpg?t=1504032514","ProductKey":"CutOffPreorderProductModel_bee4d","Category":"vegetables"},{"Brand":"JERSEY FRESH","Label":"peak seasonlocal","Title":"Bunched Beets with Tops","Link":"https://www.myapp.com/product/vegetables/bee6e-bunched-beets-with-tops","Sku":"BEE6E","Price":"$28.99 / 12 CT","Unit":"CTN","Img":"https://cdn-endpoint-website.azureedge.net/uploads/PhotoModel/28349/image/bee6e.search.jpg?t=1591972587","ProductKey":"ProductModel_bee6e","Category":"vegetables"},{"Brand":"","Label":"","Title":"Bunched Red Beets","Link":"https://www.myapp.com/product/vegetables/bee6r-bunched-red-beets","Sku":"BEE6R","Price":"$4.49 / 1 BUNCH","Unit":"BUNCH","Img":"https://cdn-endpoint-website.azureedge.net/uploads/PhotoModel/26843/image/bee6r.search.jpg?t=1587391559","ProductKey":"ProductModel_bee6r","Category":"vegetables"},{"Brand":"","Label":"","Title":"Large Candy Cane Beets","Link":"https://www.myapp.com/product/vegetables/bee7a-large-candy-cane-beets","Sku":"BEE7A","Price":"$49.99 / 25 LB","Unit":"CTN","Img":"https://cdn-endpoint-website.azureedge.net/uploads/PhotoModel/10868/image/bee7a.search.jpg?t=1465826904","ProductKey":"ProductModel_bee7a","Category":"vegetables"},{"Brand":"","Label":"","Title":"Frozen Yucca Steak-Cut Fries","Link":"https://www.myapp.com/product/vegetables/fz11-frozen-yucca-steak45cut-fries","Sku":"FZ11","Price":"$49.00 / 12 X 2.2 LB","Unit":"CTN","Img":"https://cdn-endpoint-website.azureedge.net/uploads/PhotoModel/20379/image/fz11.search.jpg?t=1525201024","ProductKey":"ProductModel_fz11","Category":"vegetables"},{"Brand":"","Label":"","Title":"Peeled Ginger","Link":"https://www.myapp.com/product/vegetables/gi6a-peeled-ginger","Sku":"GI6A","Price":"$89.99 / 1 X 5 LB","Unit":"CTN","Img":"https://cdn-endpoint-website.azureedge.net/uploads/PhotoModel/17306/image/gi6a.search.jpg?t=1501775479","ProductKey":"CutOffPreorderProductModel_gi6a","Category":"vegetables"},{"Brand":"","Label":"","Title":"Horseradish Root","Link":"https://www.myapp.com/product/vegetables/h-horseradish-root","Sku":"H","Price":"$29.99 / 5 LB","Unit":"EACH","Img":"https://cdn-endpoint-website.azureedge.net/uploads/PhotoModel/13690/image/h.search.jpg?t=1483553769","ProductKey":"CutOffPreorderProductModel_h","Category":"vegetables"},{"Brand":"","Label":"","Title":"Bulk Horseradish Master Case","Link":"https://www.myapp.com/product/vegetables/h2-bulk-horseradish-master-case","Sku":"H2","Price":"$239.99 / 50 LB","Unit":"CTN","Img":"https://cdn-endpoint-website.azureedge.net/uploads/PhotoModel/17498/image/h.search.jpg?t=1502243314","ProductKey":"ProductModel_h2","Category":"vegetables"},{"Brand":"","Label":"","Title":"Horseradish","Link":"https://www.myapp.com/product/vegetables/h2a-horseradish","Sku":"H2A","Price":"$18.99 / 1 LB","Unit":"EACH","Img":"https://cdn-endpoint-website.azureedge.net/uploads/PhotoModel/25690/image/horiginal.search.jpg?t=1583502092","ProductKey":"CutOffPreorderProductModel_h2a","Category":"vegetables"},{"Brand":"","Label":"","Title":"Jicama","Link":"https://www.myapp.com/product/vegetables/j-jicama","Sku":"J","Price":"$24.99 / 20 LB","Unit":"CTN","Img":"https://cdn-endpoint-website.azureedge.net/uploads/PhotoModel/13834/image/j.search.jpg?t=1485210795","ProductKey":"ProductModel_j","Category":"vegetables"},{"Brand":"","Label":"","Title":"Jicama","Link":"https://www.myapp.com/product/vegetables/j0-jicama","Sku":"J0","Price":"$39.99 / 35 LB","Unit":"CTN","Img":"https://cdn-endpoint-website.azureedge.net/uploads/PhotoModel/17522/image/j.search.jpg?t=1502381297","ProductKey":"ProductModel_j0","Category":"vegetables"},{"Brand":"","Label":"","Title":"Jicama with PLU","Link":"https://www.myapp.com/product/vegetables/j01-jicama-with-plu","Sku":"J01","Price":"$49.99 / 20 LB","Unit":"CTN","Img":"https://cdn-endpoint-website.azureedge.net/uploads/PhotoModel/17523/image/j.search.jpg?t=1502383111","ProductKey":"CutOffPreorderProductModel_j01","Category":"vegetables"},{"Brand":"","Label":"","Title":"1/4\" Diced Jicama Cubes","Link":"https://www.myapp.com/product/vegetables/j1e-147434-diced-jicama-cubes","Sku":"J1E","Price":"$50.89 / 2 X 5 LB","Unit":"CTN","Img":"https://cdn-endpoint-website.azureedge.net/uploads/PhotoModel/24604/image/j1e.search.jpg?t=1569525255","ProductKey":"CutOffPreorderProductModel_j1e","Category":"vegetables"},{"Brand":"","Label":"","Title":"Extra Fancy Parsnips","Link":"https://www.myapp.com/product/vegetables/par-extra-fancy-parsnips","Sku":"PAR","Price":"$25.99 / 20 LB","Unit":"CTN","Img":"https://cdn-endpoint-website.azureedge.net/uploads/PhotoModel/7811/image/par.search.jpg?t=1465837521","ProductKey":"ProductModel_par","Category":"vegetables"},{"Brand":"","Label":"","Title":"Parsnips","Link":"https://www.myapp.com/product/vegetables/par1-parsnips","Sku":"PAR.1","Price":"$2.49 / 1 LB","Unit":"CTN","Img":"https://cdn-endpoint-website.azureedge.net/uploads/PhotoModel/21112/image/par.search.jpg?t=1531855013","ProductKey":"ProductModel_par.1","Category":"vegetables"},{"Brand":"","Label":"","Title":"1/2\" Diced Parsnip","Link":"https://www.myapp.com/product/vegetables/par1-147234-diced-parsnip","Sku":"PAR1","Price":"$19.89 / 1 X 5 LB","Unit":"CTN","Img":"https://cdn-endpoint-website.azureedge.net/uploads/PhotoModel/18116/image/image-1.search.jpg?t=1504621587","ProductKey":"CutOffPreorderProductModel_par1","Category":"vegetables"},{"Brand":"","Label":"","Title":"Parsnip Batons","Link":"https://www.myapp.com/product/vegetables/par1a-parsnip-batons","Sku":"PAR1A","Price":"$81.89 / 1 X 5 LB","Unit":"CTN","Img":"https://cdn-endpoint-website.azureedge.net/uploads/PhotoModel/21593/image/par1a.search.jpg?t=1539098499","ProductKey":"CutOffPreorderProductModel_par1a","Category":"vegetables"},{"Brand":"","Label":"","Title":"Peeled Whole Parsnips","Link":"https://www.myapp.com/product/vegetables/par1b-peeled-whole-parsnips","Sku":"PAR1B","Price":"$72.89 / 4 X 5 LB","Unit":"CTN","Img":"https://cdn-endpoint-website.azureedge.net/uploads/PhotoModel/17758/image/par1b.search.jpg?t=1503524651","ProductKey":"CutOffPreorderProductModel_par1b","Category":"vegetables"},{"Brand":"","Label":"","Title":"Peeled Whole Parsnips","Link":"https://www.myapp.com/product/vegetables/par1b1-peeled-whole-parsnips","Sku":"PAR1B1","Price":"$19.89 / 5 LB","Unit":"CTN","Img":"https://cdn-endpoint-website.azureedge.net/uploads/PhotoModel/19727/image/par1b.search.jpg?t=1519842028","ProductKey":"CutOffPreorderProductModel_par1b1","Category":"vegetables"},{"Brand":"","Label":"","Title":"1/2\" Bias Cut Parsnip","Link":"https://www.myapp.com/product/vegetables/par1c-147234-bias-cut-parsnip","Sku":"PAR1C","Price":"$143.89 / 4 X 5 LB","Unit":"CTN","Img":"https://cdn-endpoint-website.azureedge.net/uploads/PhotoModel/17759/image/image-1.search.jpg?t=1503524651","ProductKey":"CutOffPreorderProductModel_par1c","Category":"vegetables"},{"Brand":"","Label":"","Title":"Parsnip Cubes","Link":"https://www.myapp.com/product/vegetables/par1e-parsnip-cubes","Sku":"PAR1E","Price":"$70.89 / 1 X 5 LB","Unit":"CTN","Img":"https://cdn-endpoint-website.azureedge.net/uploads/PhotoModel/17844/image/image-1.search.jpg?t=1503956718","ProductKey":"CutOffPreorderProductModel_par1e","Category":"vegetables"},{"Brand":"","Label":"","Title":"3/4\" Diced Parsnip","Link":"https://www.myapp.com/product/vegetables/par1j1-347434-diced-parsnip","Sku":"PAR1J1","Price":"$109.99 / 4 X 5 LB","Unit":"CTN","Img":"https://cdn-endpoint-website.azureedge.net/uploads/PhotoModel/22220/image/par1j1.search.jpg?t=1546263814","ProductKey":"CutOffPreorderProductModel_par1j1","Category":"vegetables"},{"Brand":"","Label":"","Title":"1/4\" Diced Parsnip","Link":"https://www.myapp.com/product/vegetables/par1l-147434-diced-parsnip","Sku":"PAR1L","Price":"$20.89 / 1 X 5 LB","Unit":"CTN","Img":"https://cdn-endpoint-website.azureedge.net/uploads/PhotoModel/17400/image/image-1.search.jpg?t=1501776612","ProductKey":"CutOffPreorderProductModel_par1l","Category":"vegetables"},{"Brand":"","Label":"","Title":"Parsnips","Link":"https://www.myapp.com/product/vegetables/par5-parsnips","Sku":"PAR5","Price":"$25.99 / 12 X 1 LB","Unit":"CTN","Img":"https://cdn-endpoint-website.azureedge.net/uploads/PhotoModel/19327/image/par.search.jpg?t=1511214406","ProductKey":"ProductModel_par5","Category":"vegetables"},{"Brand":"","Label":"","Title":"Lotus Root","Link":"https://www.myapp.com/product/vegetables/roo-lotus-root","Sku":"ROO","Price":"$49.99 / 10 LB","Unit":"CTN","Img":"https://cdn-endpoint-website.azureedge.net/uploads/PhotoModel/13835/image/roo.search.jpg?t=1485965937","ProductKey":"CutOffPreorderProductModel_roo","Category":"vegetables"},{"Brand":"","Label":"","Title":"Lotus Root Case","Link":"https://www.myapp.com/product/vegetables/roo0-lotus-root-case","Sku":"ROO0","Price":"$147.75 / 44 LB","Unit":"CTN","Img":"https://cdn-endpoint-website.azureedge.net/uploads/PhotoModel/16306/image/roo0.search.jpg?t=1496183918","ProductKey":"ProductModel_roo0","Category":"vegetables"},{"Brand":"","Label":"","Title":"Taro Root","Link":"https://www.myapp.com/product/vegetables/roo1-taro-root","Sku":"ROO1","Price":"$24.99 / 10 LB","Unit":"CTN","Img":"https://cdn-endpoint-website.azureedge.net/uploads/PhotoModel/17554/image/roo2.search.jpg?t=1502392303","ProductKey":"CutOffPreorderProductModel_roo1","Category":"vegetables"},{"Brand":"","Label":"","Title":"Taro Root","Link":"https://www.myapp.com/product/vegetables/roo2-taro-root","Sku":"ROO2","Price":"$39.99 / 40 LB","Unit":"CTN","Img":"https://cdn-endpoint-website.azureedge.net/uploads/PhotoModel/13889/image/roo2.search.jpg?t=1485966260","ProductKey":"ProductModel_roo2","Category":"vegetables"},{"Brand":"","Label":"","Title":"Galanga / Galangal Root","Link":"https://www.myapp.com/product/vegetables/roo4-galanga-47-galangal-root","Sku":"ROO4","Price":"$91.99 / 10 LB","Unit":"CTN","Img":"https://cdn-endpoint-website.azureedge.net/uploads/PhotoModel/13833/image/roo4.search.jpg?t=1485966105","ProductKey":"ProductModel_roo4","Category":"vegetables"},{"Brand":"","Label":"","Title":"Burdock Root","Link":"https://www.myapp.com/product/vegetables/roo5-burdock-root","Sku":"ROO5","Price":"$33.99 / 10 LB","Unit":"CTN","Img":"https://cdn-endpoint-website.azureedge.net/uploads/PhotoModel/13836/image/roo5.search.jpg?t=1485966260","ProductKey":"ProductModel_roo5","Category":"vegetables"},{"Brand":"","Label":"","Title":"Turmeric","Link":"https://www.myapp.com/product/vegetables/roo7a-turmeric","Sku":"ROO7A","Price":"$55.99 / 10 LB","Unit":"CTN","Img":"https://cdn-endpoint-website.azureedge.net/uploads/PhotoModel/7897/image/image1.search.jpg?t=1486575587","ProductKey":"ProductModel_roo7a","Category":"vegetables"},{"Brand":"","Label":"","Title":"Turmeric","Link":"https://www.myapp.com/product/vegetables/roo7a1-turmeric","Sku":"ROO7A1","Price":"$7.99 / 1 LB","Unit":"EACH","Img":"https://cdn-endpoint-website.azureedge.net/uploads/PhotoModel/14177/image/image1.search.jpg?t=1486566156","ProductKey":"ProductModel_roo7a1","Category":"vegetables"},{"Brand":"","Label":"","Title":"Salsify","Link":"https://www.myapp.com/product/vegetables/sal-salsify","Sku":"SAL","Price":"$17.99 / 11 LB","Unit":"CTN","Img":"https://cdn-endpoint-website.azureedge.net/uploads/PhotoModel/9844/image/sal.search.jpg?t=1465934882","ProductKey":"ProductModel_sal","Category":"vegetables"},{"Brand":"","Label":"","Title":"White Turnips","Link":"https://www.myapp.com/product/vegetables/tu-white-turnips","Sku":"TU","Price":"$37.99 / 25 LB","Unit":"CTN","Img":"https://cdn-endpoint-website.azureedge.net/uploads/PhotoModel/16320/image/tu.search.jpg?t=1496182157","ProductKey":"ProductModel_tu","Category":"vegetables"},{"Brand":"","Label":"","Title":"1/2\" Diced Turnips","Link":"https://www.myapp.com/product/vegetables/tu0-147234-diced-turnips","Sku":"TU0","Price":"$24.99 / 1 X 5 LB","Unit":"CTN","Img":"https://cdn-endpoint-website.azureedge.net/uploads/PhotoModel/18239/image/image-1.search.jpg?t=1504814154","ProductKey":"CutOffPreorderProductModel_tu0","Category":"vegetables"},{"Brand":"","Label":"","Title":"Baby Turnips","Link":"https://www.myapp.com/product/vegetables/tu1-baby-turnips","Sku":"TU1","Price":"$47.99 / 24 CT","Unit":"CTN","Img":"https://cdn-endpoint-website.azureedge.net/uploads/PhotoModel/10802/image/tu1.search.jpg?t=1465823522","ProductKey":"ProductModel_tu1","Category":"vegetables"},{"Brand":"","Label":"","Title":"Peeled Whole Turnips","Link":"https://www.myapp.com/product/vegetables/tu2b-peeled-whole-turnips","Sku":"TU2B","Price":"$19.99 / 1 X 5 LB","Unit":"CTN","Img":"https://cdn-endpoint-website.azureedge.net/uploads/PhotoModel/17874/image/tu2b.search.jpg?t=1503957603","ProductKey":"CutOffPreorderProductModel_tu2b","Category":"vegetables"},{"Brand":"","Label":"","Title":"Diced White Turnip 3/4\"","Link":"https://www.myapp.com/product/vegetables/tu2k-diced-white-turnip-347434","Sku":"TU2K","Price":"$109.99 / 4 X 5 LB","Unit":"CTN","Img":"https://cdn-endpoint-website.azureedge.net/uploads/PhotoModel/19871/image/image155.search.jpg?t=1518627867","ProductKey":"CutOffPreorderProductModel_tu2k","Category":"vegetables"},{"Brand":"","Label":"","Title":"1\" Cubed White Turnips","Link":"https://www.myapp.com/product/vegetables/tu2m-134-cubed-white-turnips","Sku":"TU2M","Price":"$79.99 / 1 X 5 LB","Unit":"CTN","Img":"https://cdn-endpoint-website.azureedge.net/uploads/PhotoModel/17875/image/image-1.search.jpg?t=1503957603","ProductKey":"CutOffPreorderProductModel_tu2m","Category":"vegetables"},{"Brand":"","Label":"","Title":"Rutabaga / Yellow Turnips","Link":"https://www.myapp.com/product/vegetables/tu3-rutabaga-47-yellow-turnips","Sku":"TU3","Price":"$52.99 / 50 LB","Unit":"CTN","Img":"https://cdn-endpoint-website.azureedge.net/uploads/PhotoModel/10003/image/tu3.search.jpg?t=1465823522","ProductKey":"ProductModel_tu3","Category":"vegetables"},{"Brand":"","Label":"","Title":"Diced Yellow Turnips 3/4\"","Link":"https://www.myapp.com/product/vegetables/tu3b-diced-yellow-turnips-347434","Sku":"TU3B","Price":"$106.89 / 4 X 5 LB","Unit":"CTN","Img":"https://cdn-endpoint-website.azureedge.net/uploads/PhotoModel/20556/image/image198.search.jpg?t=1526400485","ProductKey":"CutOffPreorderProductModel_tu3b","Category":"vegetables"},{"Brand":"","Label":"","Title":"1/2\" Diced Yellow Turnips","Link":"https://www.myapp.com/product/vegetables/tu5f-147234-diced-yellow-turnips","Sku":"TU5F","Price":"$29.99 / 1 X 5 LB","Unit":"CTN","Img":"https://cdn-endpoint-website.azureedge.net/uploads/PhotoModel/17412/image/image-1.search.jpg?t=1501775925","ProductKey":"CutOffPreorderProductModel_tu5f","Category":"vegetables"},{"Brand":"","Label":"","Title":"Parisienne Turnips","Link":"https://www.myapp.com/product/vegetables/tu8-parisienne-turnips","Sku":"TU8","Price":"$201.89 / 2 X 5 LB","Unit":"CTN","Img":"https://cdn-endpoint-website.azureedge.net/uploads/PhotoModel/26427/image/tu8.search.jpg?t=1586456349","ProductKey":"CutOffPreorderProductModel_tu8","Category":"vegetables"},{"Brand":"","Label":"","Title":"Yucca","Link":"https://www.myapp.com/product/vegetables/yucca-yucca","Sku":"YUCCA","Price":"$34.99 / 35 LB","Unit":"CTN","Img":"https://cdn-endpoint-website.azureedge.net/uploads/PhotoModel/13898/image/yucca.search.jpg?t=1485966259","ProductKey":"ProductModel_yucca","Category":"vegetables"},{"Brand":"","Label":"","Title":"Organic Gold Beets","Link":"https://www.myapp.com/product/vegetables/zbee1-organic-gold-beets","Sku":"ZBEE1","Price":"$39.99 / 12 CT","Unit":"CTN","Img":"https://cdn-endpoint-website.azureedge.net/uploads/PhotoModel/15413/image/zbee1.search.jpg?t=1494018289","ProductKey":"ProductModel_zbee1","Category":"vegetables"},{"Brand":"","Label":"","Title":"Organic Red Beets","Link":"https://www.myapp.com/product/vegetables/zbee2-organic-red-beets","Sku":"ZBEE2","Price":"$36.99 / 12 CT","Unit":"CTN","Img":"https://cdn-endpoint-website.azureedge.net/uploads/PhotoModel/15414/image/bee6.search.jpg?t=1494018408","ProductKey":"ProductModel_zbee2","Category":"vegetables"},{"Brand":"","Label":"","Title":"Organic Red Beets","Link":"https://www.myapp.com/product/vegetables/zbee3-organic-red-beets","Sku":"ZBEE3","Price":"$49.99 / 25 LB","Unit":"CTN","Img":"https://cdn-endpoint-website.azureedge.net/uploads/PhotoModel/15415/image/bee3.search.jpg?t=1494018407","ProductKey":"ProductModel_zbee3","Category":"vegetables"},{"Brand":"","Label":"","Title":"Organic Red Beets","Link":"https://www.myapp.com/product/vegetables/zbee3d1-organic-red-beets","Sku":"ZBEE3D1","Price":"$49.99 / 24 CT","Unit":"CTN","Img":"https://cdn-endpoint-website.azureedge.net/uploads/PhotoModel/21232/image/zbee3d1.search.jpg?t=1534447428","ProductKey":"ProductModel_zbee3d1","Category":"vegetables"},{"Brand":"","Label":"","Title":"Shredded Organic Red Beets","Link":"https://www.myapp.com/product/vegetables/zbee3e-shredded-organic-red-beets","Sku":"ZBEE3E","Price":"$89.89 / 4 X 5 LB","Unit":"CTN","Img":"https://cdn-endpoint-website.azureedge.net/uploads/PhotoModel/20583/image/bee3i.search.jpg?t=1526655061","ProductKey":"CutOffPreorderProductModel_zbee3e","Category":"vegetables"},{"Brand":"","Label":"","Title":"Organic Gold Beets","Link":"https://www.myapp.com/product/vegetables/zbee4a-organic-gold-beets","Sku":"ZBEE4A","Price":"$54.99 / 25 LB","Unit":"CTN","Img":"https://cdn-endpoint-website.azureedge.net/uploads/PhotoModel/18344/image/image293.search.jpg?t=1505336146","ProductKey":"ProductModel_zbee4a","Category":"vegetables"},{"Brand":"","Label":"","Title":"Organic Gold Beet Bunch","Link":"https://www.myapp.com/product/vegetables/zbee6a-organic-gold-beet-bunch","Sku":"ZBEE6A","Price":"$59.99 / 24 CT","Unit":"CTN","Img":"https://cdn-endpoint-website.azureedge.net/uploads/PhotoModel/16325/image/zbee6a.search.jpg?t=1496182104","ProductKey":"ProductModel_zbee6a","Category":"vegetables"},{"Brand":"","Label":"peak seasonlocal","Title":"Organic Row 7 Badger Flame Beets","Link":"https://www.myapp.com/product/vegetables/zbee7r-organic-row-7-badger-flame-beets","Sku":"ZBEE7R","Price":"$5.49 / 1 BUNCH","Unit":"EACH","Img":"https://cdn-endpoint-website.azureedge.net/uploads/PhotoModel/28362/image/zbee7r.search.jpg?t=1592229357","ProductKey":"ProductModel_zbee7r","Category":"vegetables"},{"Brand":"TAPROOT FARM","Label":"peak seasonlocal","Title":"Organic Row 7 Badger Flame Beets","Link":"https://www.myapp.com/product/vegetables/zbee9tr1-organic-row-7-badger-flame-beets","Sku":"ZBEE9TR1","Price":"$44.99 / 12 CT","Unit":"CTN","Img":"https://cdn-endpoint-website.azureedge.net/uploads/PhotoModel/28353/image/zbee9tr1.search.jpg?t=1591980408","ProductKey":"ProductModel_zbee9tr1","Category":"vegetables"},{"Brand":"","Label":"","Title":"Organic Jicama","Link":"https://www.myapp.com/product/vegetables/zj-organic-jicama","Sku":"ZJ","Price":"$49.99 / LG","Unit":"CTN","Img":"https://cdn-endpoint-website.azureedge.net/uploads/PhotoModel/22985/image/j.search.jpg?t=1551982533","ProductKey":"ProductModel_zj","Category":"vegetables"},{"Brand":"NORWICH MEADOWS FARM","Label":"peak seasonlocal","Title":"Organic Purple Kohlrabi","Link":"https://www.myapp.com/product/vegetables/zko2c-organic-purple-kohlrabi","Sku":"ZKO2C","Price":"$35.99 / 15 CT","Unit":"CTN","Img":"https://cdn-endpoint-website.azureedge.net/uploads/PhotoModel/8553/image/zk02c_1.search.jpg?t=1529431458","ProductKey":"ProductModel_zko2c","Category":"vegetables"},{"Brand":"","Label":"","Title":"Organic Turmeric","Link":"https://www.myapp.com/product/vegetables/zroo7-organic-turmeric","Sku":"ZROO7","Price":"$199.99 / 25 LB","Unit":"CTN","Img":"https://cdn-endpoint-website.azureedge.net/uploads/PhotoModel/14188/image/image136.search.jpg?t=1486580234","ProductKey":"ProductModel_zroo7","Category":"vegetables"},{"Brand":"","Label":"","Title":"Organic Turmeric","Link":"https://www.myapp.com/product/vegetables/zroo7b-organic-turmeric","Sku":"ZROO7B","Price":"$47.99 / 5 LB","Unit":"CTN","Img":"https://cdn-endpoint-website.azureedge.net/uploads/PhotoModel/20021/image/image135.search.jpg?t=1520612070","ProductKey":"ProductModel_zroo7b","Category":"vegetables"},{"Brand":"FRESH ORIGINS","Label":"","Title":"Tiny Beets","Link":"https://www.myapp.com/product/vegetables/pet2-tiny-beets","Sku":"PET2","Price":"$31.25 / 50 CT","Unit":"EACH","Img":"https://cdn-endpoint-website.azureedge.net/uploads/PhotoModel/19250/image/pet2.search.jpg?t=1510330389","ProductKey":"PreorderProductModel_pet2","Category":"vegetables"}]